glaxnimate.cpython-310-x86_64-linux-gnu.so
glaxnimate-0.5.4.dist-info/METADATA
glaxnimate-0.5.4.dist-info/WHEEL
glaxnimate-0.5.4.dist-info/top_level.txt
glaxnimate-0.5.4.dist-info/zip-safe
glaxnimate-0.5.4.dist-info/RECORD
