Metadata-Version: 2.1
Name: glaxnimate
Version: 0.5.4
Summary: Python bindings for Glaxnimate
Home-page: https://glaxnimate.mattbas.org/
Author: Mattia Basaglia
Author-email: mattia.basaglia@gmail.com
License: GNU General Public License v3 or later (GPLv3+)
Project-URL: Code, https://gitlab.com/mattbas/glaxnimate
Project-URL: Documentation, https://glaxnimate.mattbas.org/
Project-URL: Chat, https://t.me/Glaxnimate
Project-URL: Downloads, https://glaxnimate.mattbas.org/download/
Project-URL: Issues, https://gitlab.com/mattbas/glaxnimate/-/issues
Keywords: telegram stickers tgs lottie svg animation
Platform: UNKNOWN
Classifier: Programming Language :: Python :: 3
Classifier: Development Status :: 3 - Alpha
Classifier: License :: OSI Approved :: GNU General Public License v3 or later (GPLv3+)
Classifier: Operating System :: POSIX :: Linux
Classifier: Operating System :: MacOS
Classifier: Operating System :: MacOS :: MacOS X
Classifier: Operating System :: Microsoft :: Windows
Classifier: Operating System :: Microsoft :: Windows :: Windows 10
Classifier: Topic :: Multimedia :: Graphics
Requires-Python: >=3
